.coveragerc
.gitignore
CHANGES.rst
MANIFEST.in
README.rst
bootstrap.py
buildout.cfg
develop.cfg
i18n.sh
jenkins.cfg
setup.py
sources.cfg
versions.cfg
docs/LICENSE.GPL
docs/LICENSE.txt
src/collective/__init__.py
src/collective.jazzport.egg-info/PKG-INFO
src/collective.jazzport.egg-info/SOURCES.txt
src/collective.jazzport.egg-info/dependency_links.txt
src/collective.jazzport.egg-info/entry_points.txt
src/collective.jazzport.egg-info/namespace_packages.txt
src/collective.jazzport.egg-info/not-zip-safe
src/collective.jazzport.egg-info/requires.txt
src/collective.jazzport.egg-info/top_level.txt
src/collective/jazzport/__init__.py
src/collective/jazzport/browser.py
src/collective/jazzport/configure.zcml
src/collective/jazzport/interfaces.py
src/collective/jazzport/iterators.py
src/collective/jazzport/testing.py
src/collective/jazzport/upgrades.zcml
src/collective/jazzport/utils.py
src/collective/jazzport/locales/collective.jazzport.pot
src/collective/jazzport/locales/manual.pot
src/collective/jazzport/locales/en/LC_MESSAGES/collective.jazzport.mo
src/collective/jazzport/locales/en/LC_MESSAGES/collective.jazzport.po
src/collective/jazzport/locales/fi/LC_MESSAGES/collective.jazzport.mo
src/collective/jazzport/locales/fi/LC_MESSAGES/collective.jazzport.po
src/collective/jazzport/profiles/default/actions.xml
src/collective/jazzport/profiles/default/browserlayer.xml
src/collective/jazzport/profiles/default/metadata.xml
src/collective/jazzport/profiles/default/registry.xml
src/collective/jazzport/profiles/default/rolemap.xml
src/collective/jazzport/tests/__init__.py
src/collective/jazzport/tests/test_acceptance.py
src/collective/jazzport/tests/acceptance/__init__.robot
src/collective/jazzport/tests/acceptance/jazzport.robot
src/collective/jazzport/tests/acceptance/test_installed.robot