Metadata-Version: 1.1
Name: collective.jazzport
Version: 1.0.0
Summary: A yet another Zip exporter for Plone content
Home-page: https://github.com/datakurre/collective.jazzport/
Author: Asko Soukka
Author-email: asko.soukka@iki.fi
License: GPL
Platform: UNKNOWN
Classifier: Programming Language :: Python
Classifier: Programming Language :: Python :: 2.7
Classifier: Framework :: Plone :: 4.3
